{
  "view": "view_1",
  "tolerance_pixels": 10,
  "min_anchor_spacing_px": 10,
  "max_anchors_per_side_per_pair": 50,
  "total_close_boundary_pixels": 876,
  "num_pairs_with_close_boundaries": 6,
  "close_pairs": [
    {
      "label1": "fender_0",
      "label2": "handlebar_0",
      "num_close_pixels": 35,
      "anchors_label1_xy": [
        [
          105,
          71
        ]
      ],
      "anchors_label2_xy": [
        [
          110,
          60
        ],
        [
          100,
          62
        ]
      ],
      "pair_anchor_vis": "anchor_pairs/fender_0__handlebar_0.png"
    },
    {
      "label1": "fender_0",
      "label2": "headlight_0",
      "num_close_pixels": 87,
      "anchors_label1_xy": [
        [
          90,
          74
        ],
        [
          77,
          76
        ],
        [
          66,
          76
        ],
        [
          102,
          72
        ]
      ],
      "anchors_label2_xy": [
        [
          72,
          68
        ],
        [
          92,
          68
        ],
        [
          82,
          70
        ]
      ],
      "pair_anchor_vis": "anchor_pairs/fender_0__headlight_0.png"
    },
    {
      "label1": "fender_0",
      "label2": "wheel_0",
      "num_close_pixels": 200,
      "anchors_label1_xy": [
        [
          81,
          198
        ],
        [
          70,
          166
        ],
        [
          73,
          180
        ],
        [
          111,
          201
        ],
        [
          44,
          156
        ],
        [
          54,
          152
        ],
        [
          68,
          156
        ],
        [
          92,
          201
        ]
      ],
      "anchors_label2_xy": [
        [
          63,
          181
        ],
        [
          104,
          209
        ],
        [
          62,
          163
        ],
        [
          89,
          206
        ],
        [
          43,
          162
        ]
      ],
      "pair_anchor_vis": "anchor_pairs/fender_0__wheel_0.png"
    },
    {
      "label1": "handlebar_0",
      "label2": "headlight_0",
      "num_close_pixels": 98,
      "anchors_label1_xy": [
        [
          112,
          53
        ],
        [
          103,
          61
        ]
      ],
      "anchors_label2_xy": [
        [
          97,
          62
        ],
        [
          106,
          53
        ]
      ],
      "pair_anchor_vis": "anchor_pairs/handlebar_0__headlight_0.png"
    },
    {
      "label1": "seat_0",
      "label2": "storage_0",
      "num_close_pixels": 293,
      "anchors_label1_xy": [
        [
          232,
          133
        ],
        [
          244,
          136
        ],
        [
          149,
          117
        ],
        [
          160,
          125
        ],
        [
          193,
          133
        ],
        [
          257,
          135
        ],
        [
          206,
          134
        ],
        [
          218,
          134
        ],
        [
          174,
          126
        ],
        [
          256,
          125
        ]
      ],
      "anchors_label2_xy": [
        [
          230,
          137
        ],
        [
          215,
          136
        ],
        [
          160,
          125
        ],
        [
          146,
          133
        ],
        [
          265,
          140
        ],
        [
          202,
          134
        ],
        [
          190,
          129
        ],
        [
          242,
          137
        ],
        [
          175,
          126
        ],
        [
          256,
          135
        ]
      ],
      "pair_anchor_vis": "anchor_pairs/seat_0__storage_0.png"
    },
    {
      "label1": "storage_0",
      "label2": "wheel_1",
      "num_close_pixels": 200,
      "anchors_label1_xy": [
        [
          275,
          210
        ],
        [
          211,
          215
        ],
        [
          252,
          217
        ],
        [
          196,
          215
        ],
        [
          241,
          218
        ],
        [
          264,
          215
        ],
        [
          231,
          218
        ],
        [
          221,
          215
        ],
        [
          184,
          214
        ]
      ],
      "anchors_label2_xy": [
        [
          202,
          219
        ],
        [
          267,
          221
        ],
        [
          257,
          217
        ],
        [
          229,
          219
        ],
        [
          245,
          219
        ],
        [
          191,
          220
        ],
        [
          217,
          219
        ]
      ],
      "pair_anchor_vis": "anchor_pairs/storage_0__wheel_1.png"
    }
  ],
  "label_anchor_points_xy": {
    "fender_0": [
      [
        44,
        156
      ],
      [
        54,
        152
      ],
      [
        66,
        76
      ],
      [
        68,
        156
      ],
      [
        70,
        166
      ],
      [
        73,
        180
      ],
      [
        77,
        76
      ],
      [
        81,
        198
      ],
      [
        90,
        74
      ],
      [
        92,
        201
      ],
      [
        102,
        72
      ],
      [
        105,
        71
      ],
      [
        111,
        201
      ]
    ],
    "handlebar_0": [
      [
        100,
        62
      ],
      [
        103,
        61
      ],
      [
        110,
        60
      ],
      [
        112,
        53
      ]
    ],
    "headlight_0": [
      [
        72,
        68
      ],
      [
        82,
        70
      ],
      [
        92,
        68
      ],
      [
        97,
        62
      ],
      [
        106,
        53
      ]
    ],
    "seat_0": [
      [
        149,
        117
      ],
      [
        160,
        125
      ],
      [
        174,
        126
      ],
      [
        193,
        133
      ],
      [
        206,
        134
      ],
      [
        218,
        134
      ],
      [
        232,
        133
      ],
      [
        244,
        136
      ],
      [
        256,
        125
      ],
      [
        257,
        135
      ]
    ],
    "storage_0": [
      [
        146,
        133
      ],
      [
        160,
        125
      ],
      [
        175,
        126
      ],
      [
        184,
        214
      ],
      [
        190,
        129
      ],
      [
        196,
        215
      ],
      [
        202,
        134
      ],
      [
        211,
        215
      ],
      [
        215,
        136
      ],
      [
        221,
        215
      ],
      [
        230,
        137
      ],
      [
        231,
        218
      ],
      [
        241,
        218
      ],
      [
        242,
        137
      ],
      [
        252,
        217
      ],
      [
        256,
        135
      ],
      [
        264,
        215
      ],
      [
        265,
        140
      ],
      [
        275,
        210
      ]
    ],
    "wheel_0": [
      [
        43,
        162
      ],
      [
        62,
        163
      ],
      [
        63,
        181
      ],
      [
        89,
        206
      ],
      [
        104,
        209
      ]
    ],
    "wheel_1": [
      [
        191,
        220
      ],
      [
        202,
        219
      ],
      [
        217,
        219
      ],
      [
        229,
        219
      ],
      [
        245,
        219
      ],
      [
        257,
        217
      ],
      [
        267,
        221
      ]
    ]
  },
  "outputs": {
    "boundaries_with_close_highlighted": "boundaries_with_close_highlighted.png",
    "close_boundaries_only": "close_boundaries_only.png",
    "anchor_points_all": "anchor_points_all.png",
    "anchor_pairs_dir": "anchor_pairs/"
  }
}