{
  "view": "view_1",
  "tolerance_pixels": 10,
  "min_anchor_spacing_px": 10,
  "max_anchors_per_side_per_pair": 50,
  "label_centroids_xy": {
    "fender_0": [
      85.3147132169576,
      133.96492103075644
    ],
    "handlebar_0": [
      134.79232111692843,
      49.75741710296684
    ],
    "headlight_0": [
      85.35773480662984,
      57.28591160220994
    ],
    "seat_0": [
      201.04338624338624,
      123.43809523809524
    ],
    "storage_0": [
      199.783226905066,
      175.15257556406982
    ],
    "wheel_0": [
      55.366733466933866,
      212.0809619238477
    ],
    "wheel_1": [
      229.75465013286095,
      233.3153232949513
    ]
  },
  "total_close_boundary_pixels": 918,
  "num_pairs_with_close_boundaries": 6,
  "close_pairs": [
    {
      "label1": "fender_0",
      "label2": "handlebar_0",
      "num_close_pixels": 35,
      "anchors_label1_xy": [
        [
          113,
          69
        ],
        [
          101,
          72
        ]
      ],
      "anchors_label2_xy": [
        [
          102,
          61
        ],
        [
          113,
          60
        ]
      ],
      "anchors_label1_dxy": [
        [
          27.6852867830424,
          -64.96492103075644
        ],
        [
          15.6852867830424,
          -61.96492103075644
        ]
      ],
      "anchors_label2_dxy": [
        [
          -32.792321116928434,
          11.24258289703316
        ],
        [
          -21.792321116928434,
          10.24258289703316
        ]
      ],
      "pair_anchor_vis": "anchor_pairs/fender_0__handlebar_0.png"
    },
    {
      "label1": "fender_0",
      "label2": "headlight_0",
      "num_close_pixels": 87,
      "anchors_label1_xy": [
        [
          95,
          73
        ],
        [
          74,
          77
        ],
        [
          85,
          75
        ]
      ],
      "anchors_label2_xy": [
        [
          89,
          70
        ],
        [
          97,
          64
        ],
        [
          75,
          70
        ]
      ],
      "anchors_label1_dxy": [
        [
          9.6852867830424,
          -60.96492103075644
        ],
        [
          -11.3147132169576,
          -56.96492103075644
        ],
        [
          -0.3147132169575997,
          -58.96492103075644
        ]
      ],
      "anchors_label2_dxy": [
        [
          3.6422651933701644,
          12.714088397790057
        ],
        [
          11.642265193370164,
          6.714088397790057
        ],
        [
          -10.357734806629836,
          12.714088397790057
        ]
      ],
      "pair_anchor_vis": "anchor_pairs/fender_0__headlight_0.png"
    },
    {
      "label1": "fender_0",
      "label2": "wheel_0",
      "num_close_pixels": 200,
      "anchors_label1_xy": [
        [
          86,
          200
        ],
        [
          70,
          164
        ],
        [
          47,
          159
        ],
        [
          73,
          181
        ],
        [
          98,
          201
        ],
        [
          110,
          201
        ],
        [
          54,
          151
        ]
      ],
      "anchors_label2_xy": [
        [
          106,
          209
        ],
        [
          47,
          161
        ],
        [
          58,
          162
        ],
        [
          65,
          175
        ],
        [
          37,
          165
        ],
        [
          94,
          207
        ],
        [
          82,
          208
        ]
      ],
      "anchors_label1_dxy": [
        [
          0.6852867830424003,
          66.03507896924356
        ],
        [
          -15.3147132169576,
          30.035078969243557
        ],
        [
          -38.3147132169576,
          25.035078969243557
        ],
        [
          -12.3147132169576,
          47.03507896924356
        ],
        [
          12.6852867830424,
          67.03507896924356
        ],
        [
          24.6852867830424,
          67.03507896924356
        ],
        [
          -31.3147132169576,
          17.035078969243557
        ]
      ],
      "anchors_label2_dxy": [
        [
          50.633266533066134,
          -3.0809619238476955
        ],
        [
          -8.366733466933866,
          -51.080961923847696
        ],
        [
          2.6332665330661342,
          -50.080961923847696
        ],
        [
          9.633266533066134,
          -37.080961923847696
        ],
        [
          -18.366733466933866,
          -47.080961923847696
        ],
        [
          38.633266533066134,
          -5.0809619238476955
        ],
        [
          26.633266533066134,
          -4.0809619238476955
        ]
      ],
      "pair_anchor_vis": "anchor_pairs/fender_0__wheel_0.png"
    },
    {
      "label1": "handlebar_0",
      "label2": "headlight_0",
      "num_close_pixels": 95,
      "anchors_label1_xy": [
        [
          109,
          56
        ],
        [
          100,
          61
        ]
      ],
      "anchors_label2_xy": [
        [
          103,
          56
        ],
        [
          96,
          64
        ]
      ],
      "anchors_label1_dxy": [
        [
          -25.792321116928434,
          6.242582897033159
        ],
        [
          -34.792321116928434,
          11.24258289703316
        ]
      ],
      "anchors_label2_dxy": [
        [
          17.642265193370164,
          -1.2859116022099428
        ],
        [
          10.642265193370164,
          6.714088397790057
        ]
      ],
      "pair_anchor_vis": "anchor_pairs/handlebar_0__headlight_0.png"
    },
    {
      "label1": "seat_0",
      "label2": "storage_0",
      "num_close_pixels": 327,
      "anchors_label1_xy": [
        [
          212,
          134
        ],
        [
          194,
          133
        ],
        [
          258,
          132
        ],
        [
          226,
          132
        ],
        [
          177,
          127
        ],
        [
          149,
          123
        ],
        [
          244,
          136
        ],
        [
          167,
          125
        ]
      ],
      "anchors_label2_xy": [
        [
          165,
          126
        ],
        [
          148,
          131
        ],
        [
          187,
          132
        ],
        [
          237,
          137
        ],
        [
          219,
          137
        ],
        [
          263,
          133
        ],
        [
          197,
          135
        ],
        [
          254,
          139
        ],
        [
          208,
          135
        ],
        [
          175,
          128
        ]
      ],
      "anchors_label1_dxy": [
        [
          10.956613756613763,
          10.561904761904756
        ],
        [
          -7.043386243386237,
          9.561904761904756
        ],
        [
          56.95661375661376,
          8.561904761904756
        ],
        [
          24.956613756613763,
          8.561904761904756
        ],
        [
          -24.043386243386237,
          3.5619047619047564
        ],
        [
          -52.04338624338624,
          -0.43809523809524364
        ],
        [
          42.95661375661376,
          12.561904761904756
        ],
        [
          -34.04338624338624,
          1.5619047619047564
        ]
      ],
      "anchors_label2_dxy": [
        [
          -34.78322690506599,
          -49.15257556406982
        ],
        [
          -51.78322690506599,
          -44.15257556406982
        ],
        [
          -12.783226905065987,
          -43.15257556406982
        ],
        [
          37.21677309493401,
          -38.15257556406982
        ],
        [
          19.216773094934013,
          -38.15257556406982
        ],
        [
          63.21677309493401,
          -42.15257556406982
        ],
        [
          -2.7832269050659875,
          -40.15257556406982
        ],
        [
          54.21677309493401,
          -36.15257556406982
        ],
        [
          8.216773094934013,
          -40.15257556406982
        ],
        [
          -24.783226905065987,
          -47.15257556406982
        ]
      ],
      "pair_anchor_vis": "anchor_pairs/seat_0__storage_0.png"
    },
    {
      "label1": "storage_0",
      "label2": "wheel_1",
      "num_close_pixels": 211,
      "anchors_label1_xy": [
        [
          251,
          217
        ],
        [
          217,
          215
        ],
        [
          273,
          213
        ],
        [
          262,
          215
        ],
        [
          235,
          218
        ],
        [
          193,
          215
        ],
        [
          204,
          215
        ],
        [
          182,
          214
        ]
      ],
      "anchors_label2_xy": [
        [
          204,
          219
        ],
        [
          267,
          224
        ],
        [
          258,
          217
        ],
        [
          225,
          219
        ],
        [
          190,
          220
        ],
        [
          238,
          219
        ],
        [
          248,
          218
        ],
        [
          215,
          219
        ]
      ],
      "anchors_label1_dxy": [
        [
          51.21677309493401,
          41.84742443593018
        ],
        [
          17.216773094934013,
          39.84742443593018
        ],
        [
          73.21677309493401,
          37.84742443593018
        ],
        [
          62.21677309493401,
          39.84742443593018
        ],
        [
          35.21677309493401,
          42.84742443593018
        ],
        [
          -6.7832269050659875,
          39.84742443593018
        ],
        [
          4.2167730949340125,
          39.84742443593018
        ],
        [
          -17.783226905065987,
          38.84742443593018
        ]
      ],
      "anchors_label2_dxy": [
        [
          -25.754650132860945,
          -14.315323294951298
        ],
        [
          37.245349867139055,
          -9.315323294951298
        ],
        [
          28.245349867139055,
          -16.3153232949513
        ],
        [
          -4.754650132860945,
          -14.315323294951298
        ],
        [
          -39.754650132860945,
          -13.315323294951298
        ],
        [
          8.245349867139055,
          -14.315323294951298
        ],
        [
          18.245349867139055,
          -15.315323294951298
        ],
        [
          -14.754650132860945,
          -14.315323294951298
        ]
      ],
      "pair_anchor_vis": "anchor_pairs/storage_0__wheel_1.png"
    }
  ],
  "label_anchor_points_xy": {
    "fender_0": [
      [
        47,
        159
      ],
      [
        54,
        151
      ],
      [
        70,
        164
      ],
      [
        73,
        181
      ],
      [
        74,
        77
      ],
      [
        85,
        75
      ],
      [
        86,
        200
      ],
      [
        95,
        73
      ],
      [
        98,
        201
      ],
      [
        101,
        72
      ],
      [
        110,
        201
      ],
      [
        113,
        69
      ]
    ],
    "handlebar_0": [
      [
        100,
        61
      ],
      [
        102,
        61
      ],
      [
        109,
        56
      ],
      [
        113,
        60
      ]
    ],
    "headlight_0": [
      [
        75,
        70
      ],
      [
        89,
        70
      ],
      [
        96,
        64
      ],
      [
        97,
        64
      ],
      [
        103,
        56
      ]
    ],
    "seat_0": [
      [
        149,
        123
      ],
      [
        167,
        125
      ],
      [
        177,
        127
      ],
      [
        194,
        133
      ],
      [
        212,
        134
      ],
      [
        226,
        132
      ],
      [
        244,
        136
      ],
      [
        258,
        132
      ]
    ],
    "storage_0": [
      [
        148,
        131
      ],
      [
        165,
        126
      ],
      [
        175,
        128
      ],
      [
        182,
        214
      ],
      [
        187,
        132
      ],
      [
        193,
        215
      ],
      [
        197,
        135
      ],
      [
        204,
        215
      ],
      [
        208,
        135
      ],
      [
        217,
        215
      ],
      [
        219,
        137
      ],
      [
        235,
        218
      ],
      [
        237,
        137
      ],
      [
        251,
        217
      ],
      [
        254,
        139
      ],
      [
        262,
        215
      ],
      [
        263,
        133
      ],
      [
        273,
        213
      ]
    ],
    "wheel_0": [
      [
        37,
        165
      ],
      [
        47,
        161
      ],
      [
        58,
        162
      ],
      [
        65,
        175
      ],
      [
        82,
        208
      ],
      [
        94,
        207
      ],
      [
        106,
        209
      ]
    ],
    "wheel_1": [
      [
        190,
        220
      ],
      [
        204,
        219
      ],
      [
        215,
        219
      ],
      [
        225,
        219
      ],
      [
        238,
        219
      ],
      [
        248,
        218
      ],
      [
        258,
        217
      ],
      [
        267,
        224
      ]
    ]
  },
  "label_anchor_points_dxy": {
    "fender_0": [
      [
        -38.3147132169576,
        25.035078969243557
      ],
      [
        -31.3147132169576,
        17.035078969243557
      ],
      [
        -15.3147132169576,
        30.035078969243557
      ],
      [
        -12.3147132169576,
        47.03507896924356
      ],
      [
        -11.3147132169576,
        -56.96492103075644
      ],
      [
        -0.3147132169575997,
        -58.96492103075644
      ],
      [
        0.6852867830424003,
        66.03507896924356
      ],
      [
        9.6852867830424,
        -60.96492103075644
      ],
      [
        12.6852867830424,
        67.03507896924356
      ],
      [
        15.6852867830424,
        -61.96492103075644
      ],
      [
        24.6852867830424,
        67.03507896924356
      ],
      [
        27.6852867830424,
        -64.96492103075644
      ]
    ],
    "handlebar_0": [
      [
        -34.792321116928434,
        11.24258289703316
      ],
      [
        -32.792321116928434,
        11.24258289703316
      ],
      [
        -25.792321116928434,
        6.242582897033159
      ],
      [
        -21.792321116928434,
        10.24258289703316
      ]
    ],
    "headlight_0": [
      [
        -10.357734806629836,
        12.714088397790057
      ],
      [
        3.6422651933701644,
        12.714088397790057
      ],
      [
        10.642265193370164,
        6.714088397790057
      ],
      [
        11.642265193370164,
        6.714088397790057
      ],
      [
        17.642265193370164,
        -1.2859116022099428
      ]
    ],
    "seat_0": [
      [
        -52.04338624338624,
        -0.43809523809524364
      ],
      [
        -34.04338624338624,
        1.5619047619047564
      ],
      [
        -24.043386243386237,
        3.5619047619047564
      ],
      [
        -7.043386243386237,
        9.561904761904756
      ],
      [
        10.956613756613763,
        10.561904761904756
      ],
      [
        24.956613756613763,
        8.561904761904756
      ],
      [
        42.95661375661376,
        12.561904761904756
      ],
      [
        56.95661375661376,
        8.561904761904756
      ]
    ],
    "storage_0": [
      [
        -51.78322690506599,
        -44.15257556406982
      ],
      [
        -34.78322690506599,
        -49.15257556406982
      ],
      [
        -24.783226905065987,
        -47.15257556406982
      ],
      [
        -17.783226905065987,
        38.84742443593018
      ],
      [
        -12.783226905065987,
        -43.15257556406982
      ],
      [
        -6.7832269050659875,
        39.84742443593018
      ],
      [
        -2.7832269050659875,
        -40.15257556406982
      ],
      [
        4.2167730949340125,
        39.84742443593018
      ],
      [
        8.216773094934013,
        -40.15257556406982
      ],
      [
        17.216773094934013,
        39.84742443593018
      ],
      [
        19.216773094934013,
        -38.15257556406982
      ],
      [
        35.21677309493401,
        42.84742443593018
      ],
      [
        37.21677309493401,
        -38.15257556406982
      ],
      [
        51.21677309493401,
        41.84742443593018
      ],
      [
        54.21677309493401,
        -36.15257556406982
      ],
      [
        62.21677309493401,
        39.84742443593018
      ],
      [
        63.21677309493401,
        -42.15257556406982
      ],
      [
        73.21677309493401,
        37.84742443593018
      ]
    ],
    "wheel_0": [
      [
        -18.366733466933866,
        -47.080961923847696
      ],
      [
        -8.366733466933866,
        -51.080961923847696
      ],
      [
        2.6332665330661342,
        -50.080961923847696
      ],
      [
        9.633266533066134,
        -37.080961923847696
      ],
      [
        26.633266533066134,
        -4.0809619238476955
      ],
      [
        38.633266533066134,
        -5.0809619238476955
      ],
      [
        50.633266533066134,
        -3.0809619238476955
      ]
    ],
    "wheel_1": [
      [
        -39.754650132860945,
        -13.315323294951298
      ],
      [
        -25.754650132860945,
        -14.315323294951298
      ],
      [
        -14.754650132860945,
        -14.315323294951298
      ],
      [
        -4.754650132860945,
        -14.315323294951298
      ],
      [
        8.245349867139055,
        -14.315323294951298
      ],
      [
        18.245349867139055,
        -15.315323294951298
      ],
      [
        28.245349867139055,
        -16.3153232949513
      ],
      [
        37.245349867139055,
        -9.315323294951298
      ]
    ]
  },
  "outputs": {
    "boundaries_with_close_highlighted": "boundaries_with_close_highlighted.png",
    "close_boundaries_only": "close_boundaries_only.png",
    "anchor_points_all": "anchor_points_all.png",
    "anchor_pairs_dir": "anchor_pairs/"
  }
}