{
  "view": "view_3",
  "image": "sketch/views/view_3.png",
  "camera": "sketch/3d_reconstruction/view_3_cam.json",
  "H": 320,
  "W": 320,
  "apply_obj2world": false,
  "labels": {
    "wheel_0": {
      "obb_before_2d": [
        [
          128.21903019427398,
          188.24136853563675
        ],
        [
          131.4290812904486,
          189.8689521831032
        ],
        [
          129.54319062223087,
          252.2950998943541
        ],
        [
          126.56230871374777,
          242.72821392051165
        ],
        [
          171.56039074392356,
          189.40078750485634
        ],
        [
          180.9761056695957,
          191.1812005122478
        ],
        [
          179.29073967382993,
          253.0766682197521
        ],
        [
          170.0570050747391,
          243.48291703929817
        ]
      ],
      "obb_after_2d": [
        [
          127.55764156861362,
          209.99335292725834
        ],
        [
          130.67641978056278,
          214.78331195195923
        ],
        [
          129.54319062223087,
          252.2950998943541
        ],
        [
          126.56230871374777,
          242.72821392051165
        ],
        [
          170.96020729943757,
          210.9915206443624
        ],
        [
          180.30346086237074,
          215.88424130505592
        ],
        [
          179.29073967382993,
          253.07666821975207
        ],
        [
          170.0570050747391,
          243.48291703929812
        ]
      ],
      "valid_before": [
        true,
        true,
        true,
        true,
        true,
        true,
        true,
        true
      ],
      "valid_after": [
        true,
        true,
        true,
        true,
        true,
        true,
        true,
        true
      ],
      "valid_pairs": [
        true,
        true,
        true,
        true,
        true,
        true,
        true,
        true
      ],
      "valid_indices": [
        0,
        1,
        2,
        3,
        4,
        5,
        6,
        7
      ],
      "num_valid_pairs": 8,
      "overlay_image": "sketch/back_project_masks/view_3/3d_project/wheel_0_obb_before_after.png"
    },
    "wheel_1": {
      "obb_before_2d": [
        [
          198.3941727190226,
          193.4380754467283
        ],
        [
          199.3189507782934,
          255.4601660824747
        ],
        [
          223.67649126224222,
          240.0312891810105
        ],
        [
          221.61646846298228,
          163.7026870780246
        ],
        [
          132.4430998061667,
          191.71203458280215
        ],
        [
          131.2979927074274,
          254.41607390046786
        ],
        [
          138.8049020447204,
          238.4934350241267
        ],
        [
          139.94325798998298,
          161.13090019625758
        ]
      ],
      "obb_after_2d": [
        [
          198.7572904260715,
          217.79129091530118
        ],
        [
          199.3189507782934,
          255.4601660824747
        ],
        [
          223.67649126224222,
          240.0312891810105
        ],
        [
          222.42165725007456,
          193.53679113251903
        ],
        [
          131.99356706716955,
          216.32765225881485
        ],
        [
          131.2979927074274,
          254.41607390046784
        ],
        [
          138.8049020447204,
          238.4934350241267
        ],
        [
          139.49846675703998,
          191.35885955544347
        ]
      ],
      "valid_before": [
        true,
        true,
        true,
        true,
        true,
        true,
        true,
        true
      ],
      "valid_after": [
        true,
        true,
        true,
        true,
        true,
        true,
        true,
        true
      ],
      "valid_pairs": [
        true,
        true,
        true,
        true,
        true,
        true,
        true,
        true
      ],
      "valid_indices": [
        0,
        1,
        2,
        3,
        4,
        5,
        6,
        7
      ],
      "num_valid_pairs": 8,
      "overlay_image": "sketch/back_project_masks/view_3/3d_project/wheel_1_obb_before_after.png"
    },
    "fender_0": {
      "obb_before_2d": [
        [
          122.46877136852211,
          99.37925110079614
        ],
        [
          124.88762933800379,
          87.91365837454872
        ],
        [
          121.03323798995933,
          213.08906513351826
        ],
        [
          119.09765854917472,
          208.41750779952994
        ],
        [
          178.73278367585567,
          101.74404302300776
        ],
        [
          189.34119355475315,
          90.75112910041852
        ],
        [
          186.01247725462827,
          214.5471326210568
        ],
        [
          175.76176136678134,
          209.73413649240507
        ]
      ],
      "obb_after_2d": [
        [
          123.75232800134958,
          116.45087905417054
        ],
        [
          126.35688368111819,
          107.5195110605273
        ],
        [
          122.5193313783223,
          232.65701511811875
        ],
        [
          120.39402809895117,
          225.4603459063964
        ],
        [
          179.93225495180866,
          118.64742688813038
        ],
        [
          190.70008993279168,
          110.1354096568481
        ],
        [
          187.38642662216438,
          233.89430570758128
        ],
        [
          176.97285975080695,
          226.60925806080715
        ]
      ],
      "valid_before": [
        true,
        true,
        true,
        true,
        true,
        true,
        true,
        true
      ],
      "valid_after": [
        true,
        true,
        true,
        true,
        true,
        true,
        true,
        true
      ],
      "valid_pairs": [
        true,
        true,
        true,
        true,
        true,
        true,
        true,
        true
      ],
      "valid_indices": [
        0,
        1,
        2,
        3,
        4,
        5,
        6,
        7
      ],
      "num_valid_pairs": 8,
      "overlay_image": "sketch/back_project_masks/view_3/3d_project/fender_0_obb_before_after.png"
    },
    "unknown_0": {
      "obb_before_2d": [
        [
          121.02733941255612,
          193.61267690728428
        ],
        [
          127.37461826321693,
          200.66252143236662
        ],
        [
          125.03720457127525,
          277.4653873999256
        ],
        [
          119.36866034727485,
          247.4164204356667
        ],
        [
          178.9164869216573,
          195.10579988747907
        ],
        [
          209.42307360557766,
          202.68138137876184
        ],
        [
          207.49207088243494,
          278.4021702674298
        ],
        [
          177.45972166124136,
          248.37626155180766
        ]
      ],
      "obb_after_2d": [
        [
          122.41519306085664,
          211.9140048558506
        ],
        [
          129.33845061032358,
          226.71073140897664
        ],
        [
          127.01472368694203,
          303.4809717077951
        ],
        [
          120.76330641793604,
          265.7018931886488
        ],
        [
          180.21093867424432,
          213.22288834333898
        ],
        [
          211.19922431114338,
          228.35794140154016
        ],
        [
          209.2800663428373,
          304.04699928601065
        ],
        [
          178.76032091953724,
          266.47779964208115
        ]
      ],
      "valid_before": [
        true,
        true,
        true,
        true,
        true,
        true,
        true,
        true
      ],
      "valid_after": [
        true,
        true,
        true,
        true,
        true,
        true,
        true,
        true
      ],
      "valid_pairs": [
        true,
        true,
        true,
        true,
        true,
        true,
        true,
        true
      ],
      "valid_indices": [
        0,
        1,
        2,
        3,
        4,
        5,
        6,
        7
      ],
      "num_valid_pairs": 8,
      "overlay_image": "sketch/back_project_masks/view_3/3d_project/unknown_0_obb_before_after.png"
    },
    "handlebar_0": {
      "obb_before_2d": [
        [
          77.44575340821147,
          91.46649042051091
        ],
        [
          75.2884603789403,
          66.04894520076913
        ],
        [
          73.7768935444872,
          93.28440294367547
        ],
        [
          76.10404815399278,
          116.74606909894521
        ],
        [
          218.5088097348974,
          97.54056324797119
        ],
        [
          229.39197675131743,
          73.35131198016548
        ],
        [
          230.74618498838493,
          99.99040904607443
        ],
        [
          219.56453965266695,
          122.30224541363768
        ]
      ],
      "obb_after_2d": [
        [
          78.57086876418008,
          105.79339893688267
        ],
        [
          76.52235463973122,
          81.75859080654061
        ],
        [
          75.03582266777116,
          109.25688144025193
        ],
        [
          77.24994793191621,
          131.2911576374861
        ],
        [
          219.45832671453385,
          111.51601656738538
        ],
        [
          230.41627801587458,
          88.63941447492937
        ],
        [
          231.78765805781399,
          115.52728438064841
        ],
        [
          220.52882570476623,
          136.48520537291574
        ]
      ],
      "valid_before": [
        true,
        true,
        true,
        true,
        true,
        true,
        true,
        true
      ],
      "valid_after": [
        true,
        true,
        true,
        true,
        true,
        true,
        true,
        true
      ],
      "valid_pairs": [
        true,
        true,
        true,
        true,
        true,
        true,
        true,
        true
      ],
      "valid_indices": [
        0,
        1,
        2,
        3,
        4,
        5,
        6,
        7
      ],
      "num_valid_pairs": 8,
      "overlay_image": "sketch/back_project_masks/view_3/3d_project/handlebar_0_obb_before_after.png"
    },
    "headlight_0": {
      "obb_before_2d": [
        [
          129.9212050951361,
          88.7986642357102
        ],
        [
          132.04790259151548,
          80.92605044029096
        ],
        [
          130.8682593176408,
          119.76631739980027
        ],
        [
          128.83382516258308,
          124.46704182684937
        ],
        [
          177.08122940348701,
          90.86941720432154
        ],
        [
          183.36022653713871,
          83.24964848064228
        ],
        [
          182.3105806863694,
          121.75068168311451
        ],
        [
          176.10362384344631,
          126.25149841685979
        ]
      ],
      "obb_after_2d": [
        [
          130.9692166632356,
          102.85354659284339
        ],
        [
          133.1868763790403,
          96.24276402372018
        ],
        [
          132.01126946794017,
          135.07412730256607
        ],
        [
          129.88524819551156,
          138.51439453560837
        ],
        [
          178.07123567371312,
          104.80793193537139
        ],
        [
          184.43052374817697,
          98.42826713990036
        ],
        [
          183.3845698702021,
          136.92054260742214
        ],
        [
          177.09677436952262,
          140.182597155716
        ]
      ],
      "valid_before": [
        true,
        true,
        true,
        true,
        true,
        true,
        true,
        true
      ],
      "valid_after": [
        true,
        true,
        true,
        true,
        true,
        true,
        true,
        true
      ],
      "valid_pairs": [
        true,
        true,
        true,
        true,
        true,
        true,
        true,
        true
      ],
      "valid_indices": [
        0,
        1,
        2,
        3,
        4,
        5,
        6,
        7
      ],
      "num_valid_pairs": 8,
      "overlay_image": "sketch/back_project_masks/view_3/3d_project/headlight_0_obb_before_after.png"
    },
    "storage_0": {
      "obb_before_2d": [
        [
          191.9267736457384,
          130.46840845665795
        ],
        [
          191.9776099336911,
          225.1360782624492
        ],
        [
          239.00256739375118,
          198.26578112247853
        ],
        [
          236.45858212359963,
          57.63063071409216
        ],
        [
          123.10230395953117,
          127.91368119489624
        ],
        [
          120.62847479790815,
          223.6651207227041
        ],
        [
          130.14704689967056,
          195.48890180787612
        ],
        [
          133.37280725323393,
          52.45500761031394
        ]
      ],
      "obb_after_2d": [
        [
          192.9527022515182,
          145.0998639508939
        ],
        [
          193.04061853286953,
          240.1888039887372
        ],
        [
          240.54382899305455,
          221.30211699355442
        ],
        [
          237.92331280035174,
          79.69312188765156
        ],
        [
          124.21748189858326,
          142.72334647604572
        ],
        [
          121.78739066856451,
          238.90656513454223
        ],
        [
          131.91171659493608,
          218.97017046582116
        ],
        [
          135.03791359920183,
          74.92513865142449
        ]
      ],
      "valid_before": [
        true,
        true,
        true,
        true,
        true,
        true,
        true,
        true
      ],
      "valid_after": [
        true,
        true,
        true,
        true,
        true,
        true,
        true,
        true
      ],
      "valid_pairs": [
        true,
        true,
        true,
        true,
        true,
        true,
        true,
        true
      ],
      "valid_indices": [
        0,
        1,
        2,
        3,
        4,
        5,
        6,
        7
      ],
      "num_valid_pairs": 8,
      "overlay_image": "sketch/back_project_masks/view_3/3d_project/storage_0_obb_before_after.png"
    },
    "unknown_1": {
      "obb_before_2d": [
        [
          150.87153108650705,
          132.19754665135815
        ],
        [
          152.3222817294381,
          139.02992773918032
        ],
        [
          144.84511198665595,
          261.78403453029205
        ],
        [
          143.76141057077837,
          251.27849288217988
        ],
        [
          207.00047988733198,
          134.24941809076353
        ],
        [
          210.57373050628965,
          141.09101848975496
        ],
        [
          198.57917527149985,
          262.5423043356893
        ],
        [
          195.6842335175298,
          252.10536671281173
        ]
      ],
      "obb_after_2d": [
        [
          150.86039460148928,
          144.80615096828765
        ],
        [
          152.35494774823,
          152.3466596128199
        ],
        [
          144.66570765871833,
          277.4504806821698
        ],
        [
          143.5590231738284,
          266.1108617784098
        ],
        [
          208.6195106868076,
          146.7915567032855
        ],
        [
          212.36410913141827,
          154.33159861333567
        ],
        [
          199.89195975056032,
          278.0801866893511
        ],
        [
          196.87383278578795,
          266.8231693727555
        ]
      ],
      "valid_before": [
        true,
        true,
        true,
        true,
        true,
        true,
        true,
        true
      ],
      "valid_after": [
        true,
        true,
        true,
        true,
        true,
        true,
        true,
        true
      ],
      "valid_pairs": [
        true,
        true,
        true,
        true,
        true,
        true,
        true,
        true
      ],
      "valid_indices": [
        0,
        1,
        2,
        3,
        4,
        5,
        6,
        7
      ],
      "num_valid_pairs": 8,
      "overlay_image": "sketch/back_project_masks/view_3/3d_project/unknown_1_obb_before_after.png"
    },
    "seat_0": {
      "obb_before_2d": [
        [
          189.09129888556183,
          108.66592327085218
        ],
        [
          189.08457902779895,
          120.8151983902332
        ],
        [
          212.8347032450419,
          78.02535143332834
        ],
        [
          212.7020047447737,
          62.80073289330727
        ],
        [
          134.46163056571413,
          106.43156722054641
        ],
        [
          134.19617275004754,
          118.68645699022525
        ],
        [
          142.91799377867673,
          74.77904612410863
        ],
        [
          143.20458627393546,
          59.38884767591631
        ]
      ],
      "obb_after_2d": [
        [
          189.99444587705918,
          121.5282366870283
        ],
        [
          189.99196436480662,
          133.7259434717161
        ],
        [
          213.96245026797425,
          94.54456200450261
        ],
        [
          213.8232163792926,
          79.24061679565749
        ],
        [
          135.42684340162262,
          119.4183821227804
        ],
        [
          135.1662125004345,
          131.72265136144213
        ],
        [
          144.1474527208408,
          91.50416639122776
        ],
        [
          144.42629474459477,
          76.0326468632252
        ]
      ],
      "valid_before": [
        true,
        true,
        true,
        true,
        true,
        true,
        true,
        true
      ],
      "valid_after": [
        true,
        true,
        true,
        true,
        true,
        true,
        true,
        true
      ],
      "valid_pairs": [
        true,
        true,
        true,
        true,
        true,
        true,
        true,
        true
      ],
      "valid_indices": [
        0,
        1,
        2,
        3,
        4,
        5,
        6,
        7
      ],
      "num_valid_pairs": 8,
      "overlay_image": "sketch/back_project_masks/view_3/3d_project/seat_0_obb_before_after.png"
    }
  }
}