{
  "0": {
    "label": "fender_0",
    "color_rgb": [
      0.12156862745098039,
      0.4666666666666667,
      0.7058823529411765
    ]
  },
  "1": {
    "label": "wheel_1",
    "color_rgb": [
      0.9686274509803922,
      0.7137254901960784,
      0.8235294117647058
    ]
  },
  "2": {
    "label": "seat_0",
    "color_rgb": [
      1.0,
      0.7333333333333333,
      0.47058823529411764
    ]
  },
  "3": {
    "label": "wheel_0",
    "color_rgb": [
      0.8901960784313725,
      0.4666666666666667,
      0.7607843137254902
    ]
  },
  "4": {
    "label": "fender_0",
    "color_rgb": [
      0.12156862745098039,
      0.4666666666666667,
      0.7058823529411765
    ]
  },
  "5": {
    "label": "fender_0",
    "color_rgb": [
      0.12156862745098039,
      0.4666666666666667,
      0.7058823529411765
    ]
  },
  "6": {
    "label": "fender_0",
    "color_rgb": [
      0.12156862745098039,
      0.4666666666666667,
      0.7058823529411765
    ]
  },
  "7": {
    "label": "handlebar_0",
    "color_rgb": [
      0.6823529411764706,
      0.7803921568627451,
      0.9098039215686274
    ]
  },
  "8": {
    "label": "headlight_0",
    "color_rgb": [
      1.0,
      0.4980392156862745,
      0.054901960784313725
    ]
  },
  "9": {
    "label": "fender_0",
    "color_rgb": [
      0.12156862745098039,
      0.4666666666666667,
      0.7058823529411765
    ]
  },
  "10": {
    "label": "wheel_0",
    "color_rgb": [
      0.8901960784313725,
      0.4666666666666667,
      0.7607843137254902
    ]
  },
  "11": {
    "label": "wheel_1",
    "color_rgb": [
      0.9686274509803922,
      0.7137254901960784,
      0.8235294117647058
    ]
  },
  "12": {
    "label": "fender_0",
    "color_rgb": [
      0.12156862745098039,
      0.4666666666666667,
      0.7058823529411765
    ]
  },
  "13": {
    "label": "wheel_0",
    "color_rgb": [
      0.8901960784313725,
      0.4666666666666667,
      0.7607843137254902
    ]
  },
  "14": {
    "label": "seat_0",
    "color_rgb": [
      1.0,
      0.7333333333333333,
      0.47058823529411764
    ]
  },
  "15": {
    "label": "wheel_0",
    "color_rgb": [
      0.8901960784313725,
      0.4666666666666667,
      0.7607843137254902
    ]
  },
  "16": {
    "label": "wheel_1",
    "color_rgb": [
      0.9686274509803922,
      0.7137254901960784,
      0.8235294117647058
    ]
  },
  "17": {
    "label": "fender_0",
    "color_rgb": [
      0.12156862745098039,
      0.4666666666666667,
      0.7058823529411765
    ]
  },
  "18": {
    "label": "handlebar_0",
    "color_rgb": [
      0.6823529411764706,
      0.7803921568627451,
      0.9098039215686274
    ]
  },
  "19": {
    "label": "seat_0",
    "color_rgb": [
      1.0,
      0.7333333333333333,
      0.47058823529411764
    ]
  },
  "20": {
    "label": "unknown_0",
    "color_rgb": [
      0.2,
      0.2,
      0.2
    ]
  },
  "21": {
    "label": "unknown_1",
    "color_rgb": [
      0.2,
      0.2,
      0.2
    ]
  },
  "22": {
    "label": "unknown_2",
    "color_rgb": [
      0.2,
      0.2,
      0.2
    ]
  },
  "23": {
    "label": "unknown_3",
    "color_rgb": [
      0.2,
      0.2,
      0.2
    ]
  },
  "24": {
    "label": "unknown_4",
    "color_rgb": [
      0.2,
      0.2,
      0.2
    ]
  },
  "25": {
    "label": "unknown_5",
    "color_rgb": [
      0.2,
      0.2,
      0.2
    ]
  },
  "26": {
    "label": "unknown_6",
    "color_rgb": [
      0.2,
      0.2,
      0.2
    ]
  },
  "27": {
    "label": "unknown_7",
    "color_rgb": [
      0.2,
      0.2,
      0.2
    ]
  }
}